odoo10_addon_purchase_order_revision-10.0.1.0.0-py2.7-nspkg.pth
odoo/addons/purchase_order_revision/README.rst
odoo/addons/purchase_order_revision/__init__.py
odoo/addons/purchase_order_revision/__manifest__.py
odoo/addons/purchase_order_revision/hooks.py
odoo/addons/purchase_order_revision/i18n/bg.po
odoo/addons/purchase_order_revision/i18n/ca.po
odoo/addons/purchase_order_revision/i18n/da.po
odoo/addons/purchase_order_revision/i18n/de.po
odoo/addons/purchase_order_revision/i18n/es.po
odoo/addons/purchase_order_revision/i18n/fi.po
odoo/addons/purchase_order_revision/i18n/fr.po
odoo/addons/purchase_order_revision/i18n/fr_CH.po
odoo/addons/purchase_order_revision/i18n/fr_FR.po
odoo/addons/purchase_order_revision/i18n/hr.po
odoo/addons/purchase_order_revision/i18n/hr_HR.po
odoo/addons/purchase_order_revision/i18n/it.po
odoo/addons/purchase_order_revision/i18n/nb.po
odoo/addons/purchase_order_revision/i18n/nl.po
odoo/addons/purchase_order_revision/i18n/pt.po
odoo/addons/purchase_order_revision/i18n/pt_BR.po
odoo/addons/purchase_order_revision/i18n/pt_PT.po
odoo/addons/purchase_order_revision/i18n/purchase_order_revision.pot
odoo/addons/purchase_order_revision/i18n/sk.po
odoo/addons/purchase_order_revision/i18n/sl.po
odoo/addons/purchase_order_revision/i18n/tr.po
odoo/addons/purchase_order_revision/i18n/tr_TR.po
odoo/addons/purchase_order_revision/i18n/zh_CN.po
odoo/addons/purchase_order_revision/models/__init__.py
odoo/addons/purchase_order_revision/models/purchase_order.py
odoo/addons/purchase_order_revision/static/description/icon.png
odoo/addons/purchase_order_revision/tests/__init__.py
odoo/addons/purchase_order_revision/tests/test_purchase_order_revision.py
odoo/addons/purchase_order_revision/views/purchase_views.xml
odoo10_addon_purchase_order_revision-10.0.1.0.0.dist-info/DESCRIPTION.rst
odoo10_addon_purchase_order_revision-10.0.1.0.0.dist-info/METADATA
odoo10_addon_purchase_order_revision-10.0.1.0.0.dist-info/RECORD
odoo10_addon_purchase_order_revision-10.0.1.0.0.dist-info/WHEEL
odoo10_addon_purchase_order_revision-10.0.1.0.0.dist-info/metadata.json
odoo10_addon_purchase_order_revision-10.0.1.0.0.dist-info/namespace_packages.txt
odoo10_addon_purchase_order_revision-10.0.1.0.0.dist-info/top_level.txt
